license
xtl_read_assistant/__init__.py
xtl_read_assistant/__main__.py
xtl_read_assistant/hotkey.py
xtl_read_assistant/log_revision.py
xtl_read_assistant/read_assist.py
xtl_read_assistant/read_assistant.py
xtl_read_assistant-0.0.2.dist-info/entry_points.txt
xtl_read_assistant-0.0.2.dist-info/license
xtl_read_assistant-0.0.2.dist-info/WHEEL
xtl_read_assistant-0.0.2.dist-info/METADATA
xtl_read_assistant-0.0.2.dist-info/RECORD
