Metadata-Version: 2.1
Name: xtl-read-assistant
Version: 0.0.2
Summary: X as a third language reading assistant
Home-page: https://github.com/ffreemt/xtl-read-assistant
License: MIT
Keywords: mt,language,learning
Author: ffreemt
Requires-Python: >=3.6,<4.0
Classifier: Environment :: Console
Classifier: License :: OSI Approved :: MIT License
Classifier: Operating System :: OS Independent
Classifier: Programming Language :: Python :: 3
Classifier: Programming Language :: Python :: 3.6
Classifier: Programming Language :: Python :: 3.7
Classifier: Programming Language :: Python :: 3.8
Classifier: Topic :: Software Development :: Libraries :: Python Modules
Requires-Dist: absl-py (>=0.9.0,<0.10.0)
Requires-Dist: deepl-tr-async (>=0.0.2,<0.0.3)
Requires-Dist: environs (>=7.3.1,<8.0.0)
Requires-Dist: janus (>=0.4.0,<0.5.0)
Requires-Dist: logzero (>=1.5.0,<2.0.0)
Requires-Dist: polyglot (>=16.7.4,<17.0.0)
Requires-Dist: pynput (>=1.6.8,<2.0.0)
Requires-Dist: pyperclip (>=1.7.0,<2.0.0)
Requires-Dist: python-dotenv (>=0.12.0,<0.13.0)
Project-URL: Repository, https://github.com/ffreemt/xtl-read-assistant
